odoo_connector/__init__.py
odoo_connector/api.py
odoo_connector_datoulobase-0.1.0.dist-info/licenses/LICENSE
odoo_connector_datoulobase-0.1.0.dist-info/METADATA
odoo_connector_datoulobase-0.1.0.dist-info/WHEEL
odoo_connector_datoulobase-0.1.0.dist-info/top_level.txt
odoo_connector_datoulobase-0.1.0.dist-info/RECORD
