Metadata-Version: 2.4
Name: odoo-connector-datoulobase
Version: 0.1.0
Summary: A simple and clean Python connector for Odoo XML-RPC API
Home-page: https://github.com/mistermerlin/odoo_connector.git
Author: D. Ben Aziz Ouattara (Datoulobase)
Author-email: datoulobaben@gmail.com
Classifier: Programming Language :: Python :: 3
Classifier: License :: OSI Approved :: MIT License
Classifier: Operating System :: OS Independent
Requires-Python: >=3.6
License-File: LICENSE
Dynamic: author
Dynamic: author-email
Dynamic: classifier
Dynamic: description
Dynamic: description-content-type
Dynamic: home-page
Dynamic: license-file
Dynamic: requires-python
Dynamic: summary
